hpic-0.1.0.dist-info/METADATA
hpic-0.1.0.dist-info/WHEEL
hpic-0.1.0.dist-info/entry_points.txt
hpic-0.1.0.dist-info/licenses/LICENSE
hpic/__init__.py
hpic/exception/__init__.py
hpic/hpic.py
hpic/playwright_manager/__init__.py
hpic/playwright_manager/playwright_manager.py
hpic-0.1.0.dist-info/RECORD
