Metadata-Version: 2.1
Name: hpic
Version: 0.1.0
Summary: use playwright to render html page into pictures.
Author-Email: Kyoku <kyokukong@outlook.com>
License: MIT
Requires-Python: >=3.12
Requires-Dist: jinja2>=3.1.4
Requires-Dist: playwright>=1.48.0
